catsup/__init__.py
catsup/cli.py
catsup/compat.py
catsup/deploy.py
catsup/logger.py
catsup/models.py
catsup/options.py
catsup/server.py
catsup/utils.py
catsup/generator/__init__.py
catsup/generator/renderer.py
catsup/generator/utils.py
catsup/parser/__init__.py
catsup/parser/config.py
catsup/parser/themes.py
catsup/parser/utils.py
catsup/reader/__init__.py
catsup/reader/html.py
catsup/reader/markdown.py
catsup/reader/meta.py
catsup/reader/txt.py
catsup/reader/utils.py
catsup/templates/config.json
catsup/templates/feed.xml
catsup/templates/filters.py
catsup/templates/utils.html
catsup/themes/__init__.py
catsup/themes/__init__.pyc
catsup/themes/install.py
catsup/themes/utils.py
catsup/themes/utils.pyc
catsup/themes/__pycache__/__init__.cpython-36.pyc
catsup/themes/__pycache__/utils.cpython-36.pyc
catsup/themes/sealscript/.git
catsup/themes/sealscript/.gitignore
catsup/themes/sealscript/README.md
catsup/themes/sealscript/theme.py
catsup/themes/sealscript/static/favicon.ico
catsup/themes/sealscript/static/robots.txt
catsup/themes/sealscript/static/css/pygments_style.css
catsup/themes/sealscript/static/css/style.css
catsup/themes/sealscript/static/image/background-stripes.png
catsup/themes/sealscript/static/image/body_bg.png
catsup/themes/sealscript/static/image/body_dark_bg.png
catsup/themes/sealscript/static/image/go_bg.png
catsup/themes/sealscript/static/image/ic16_github.png
catsup/themes/sealscript/static/image/ic16_rss.png
catsup/themes/sealscript/static/image/ic16_twitter.png
catsup/themes/sealscript/static/image/mask.png
catsup/themes/sealscript/static/image/nav_bg.png
catsup/themes/sealscript/templates/404.html
catsup/themes/sealscript/templates/archive.html
catsup/themes/sealscript/templates/layout.html
catsup/themes/sealscript/templates/page.html
catsup/themes/sealscript/templates/post.html
catsup/themes/sealscript/templates/tag.html
catsup-0.3.11.dist-info/DESCRIPTION.rst
catsup-0.3.11.dist-info/METADATA
catsup-0.3.11.dist-info/RECORD
catsup-0.3.11.dist-info/WHEEL
catsup-0.3.11.dist-info/entry_points.txt
catsup-0.3.11.dist-info/metadata.json
catsup-0.3.11.dist-info/top_level.txt
