Metadata-Version: 2.0
Name: catsup
Version: 0.3.11
Summary: Catsup: a lightweight static site generator
Home-page: https://github.com/whtsky/Catsup
Author: whtsky
Author-email: whtsky@me.com
License: MIT License
Keywords: catsup,blog,site,static,static blog,static site,generator
Platform: UNKNOWN
Classifier: Development Status :: 4 - Beta
Classifier: Environment :: Console
Classifier: License :: OSI Approved :: MIT License
Classifier: Operating System :: MacOS
Classifier: Operating System :: POSIX
Classifier: Operating System :: POSIX :: Linux
Classifier: Programming Language :: Python
Classifier: Programming Language :: Python :: 2.7
Classifier: Programming Language :: Python :: 3.3
Classifier: Programming Language :: Python :: 3.4
Classifier: Programming Language :: Python :: 3.5
Classifier: Programming Language :: Python :: 3.6
Requires-Dist: argh (==0.24.1)
Requires-Dist: docopt (==0.6.1)
Requires-Dist: houdini.py (==0.1.0)
Requires-Dist: Jinja2 (==2.7.2)
Requires-Dist: MarkupSafe (==0.18)
Requires-Dist: misaka (==1.0.2)
Requires-Dist: parguments (==0.3.2)
Requires-Dist: pathtools (==0.1.2)
Requires-Dist: Pygments (==1.6)
Requires-Dist: PyYAML (==3.10)
Requires-Dist: tornado (==3.2)
Requires-Dist: ujson (==1.33)
Requires-Dist: watchdog (==0.7.0)
